nanoset.cpython-38-x86_64-linux-gnu.so
nanoset-0.2.1.dist-info/COPYING
nanoset-0.2.1.dist-info/top_level.txt
nanoset-0.2.1.dist-info/RECORD
nanoset-0.2.1.dist-info/METADATA
nanoset-0.2.1.dist-info/WHEEL
