Metadata-Version: 2.1
Name: nanoset
Version: 0.2.1
Summary: A memory-optimized wrapper for Python sets likely to be empty.
Home-page: https://github.com/althonos/nanoset.py
Author: Martin Larralde
Author-email: martin.larralde@embl.de
License: MIT
Keywords: Python,set,memory,wrapper,optimisation
Platform: any
Classifier: Development Status :: 4 - Beta
Classifier: Intended Audience :: Developers
Classifier: License :: OSI Approved :: MIT License
Classifier: Operating System :: OS Independent
Classifier: Programming Language :: Rust
Classifier: Programming Language :: Python :: 3.5
Classifier: Programming Language :: Python :: 3.6
Classifier: Programming Language :: Python :: 3.7
Classifier: Programming Language :: Python :: 3.8
Classifier: Programming Language :: Python :: Implementation :: CPython
Classifier: Topic :: Scientific/Engineering :: Medical Science Apps.
Classifier: Topic :: Software Development :: Libraries :: Python Modules
Requires-Python: >=3.5.*
